[
  {
    "volumeChange": "",
    "floorChange": "",
    "collection": "The Warlords of Champions Tactics",
    "volume": "1,442  ETH",
    "floorPrice": "0.227  ETH",
    "items": "10K",
    "owners": "4.6K"
  },
  {
    "volumeChange": "",
    "floorChange": "",
    "collection": "Azuki",
    "volume": "1,316  ETH",
    "floorPrice": "5.79  ETH",
    "items": "10K",
    "owners": "4.4K"
  },
  {
    "volumeChange": "-7.5%",
    "floorChange": "-1.7%",
    "collection": "MutantApeYachtClub",
    "volume": "954.5  ETH",
    "floorPrice": "5.23  ETH",
    "items": "19.5K",
    "owners": "11.8K"
  },
  {
    "volumeChange": "+41.7%",
    "floorChange": "+1%",
    "collection": "Pudgy Penguins",
    "volume": "521  ETH",
    "floorPrice": "10.6  ETH",
    "items": "8.9K",
    "owners": "4.6K"
  },
  {
    "volumeChange": "-18.2%",
    "floorChange": "+3.5%",
    "collection": "DeGods",
    "volume": "491.3  ETH",
    "floorPrice": "2.75  ETH",
    "items": "9K",
    "owners": "2.6K"
  },
  {
    "volumeChange": "",
    "floorChange": "",
    "collection": "OVERWORLD INCARNA",
    "volume": "385.2  ETH",
    "floorPrice": "1.799  ETH",
    "items": "6K",
    "owners": "2.2K"
  },
  {
    "volumeChange": "-26.9%",
    "floorChange": "+1.6%",
    "collection": "MATR1X KUKU",
    "volume": "377.7  ETH",
    "floorPrice": "3.15  ETH",
    "items": "6.7K",
    "owners": "1.9K"
  },
  {
    "volumeChange": "-64.5%",
    "floorChange": "-2.7%",
    "collection": "Bored Ape Yacht Club",
    "volume": "232.4  ETH",
    "floorPrice": "26.26  ETH",
    "items": "10K",
    "owners": "5.8K"
  },
  {
    "volumeChange": "",
    "floorChange": "",
    "collection": "Untitled",
    "volume": "130.1  ETH",
    "floorPrice": "0.092  ETH",
    "items": "3.9K",
    "owners": "2K"
  },
  {
    "volumeChange": "-30.3%",
    "floorChange": "-4.3%",
    "collection": "ALPHA PRESTIGE",
    "volume": "125.1  ETH",
    "floorPrice": "13.3  ETH",
    "items": "500",
    "owners": "406"
  },
  {
    "volumeChange": "-65.1%",
    "floorChange": "-8.3%",
    "collection": "Moonbirds",
    "volume": "120  ETH",
    "floorPrice": "1.88  ETH",
    "items": "10K",
    "owners": "5.9K"
  },
  {
    "volumeChange": "+111.3%",
    "floorChange": "-24.2%",
    "collection": "raW Pass",
    "volume": "116.3  ETH",
    "floorPrice": "0.16  ETH",
    "items": "5.6K",
    "owners": "1.8K"
  },
  {
    "volumeChange": "+5,352.1%",
    "floorChange": "-42%",
    "collection": "KENTARO WAVES",
    "volume": "107  ETH",
    "floorPrice": "0.58  ETH",
    "items": "500",
    "owners": "396"
  },
  {
    "volumeChange": "",
    "floorChange": "",
    "collection": "Creepz by OVERLORD",
    "volume": "92.14  ETH",
    "floorPrice": "3.45  ETH",
    "items": "9.6K",
    "owners": "2.4K"
  },
  {
    "volumeChange": "+42.7%",
    "floorChange": "-9.1%",
    "collection": "Sugartown Oras",
    "volume": "86.03  ETH",
    "floorPrice": "0.49  ETH",
    "items": "6.1K",
    "owners": "1K"
  },
  {
    "volumeChange": "-52.4%",
    "floorChange": "-3.1%",
    "collection": "Lil Pudgys",
    "volume": "83.29  ETH",
    "floorPrice": "0.939  ETH",
    "items": "21.4K",
    "owners": "8K"
  },
  {
    "volumeChange": "-6.7%",
    "floorChange": "-11.3%",
    "collection": "Poglin: Nycra",
    "volume": "69.55  ETH",
    "floorPrice": "0.195  ETH",
    "items": "5.6K",
    "owners": "2.4K"
  },
  {
    "volumeChange": "-40.4%",
    "floorChange": "-3.6%",
    "collection": "Captainz",
    "volume": "62.6  ETH",
    "floorPrice": "4.5  ETH",
    "items": "10K",
    "owners": "4.1K"
  },
  {
    "volumeChange": "+408.6%",
    "floorChange": "-0.9%",
    "collection": "Redacted Remilio Babies",
    "volume": "61.38  ETH",
    "floorPrice": "0.53  ETH",
    "items": "10K",
    "owners": "2.7K"
  },
  {
    "volumeChange": "",
    "floorChange": "",
    "collection": "Library Onchain",
    "volume": "58.37  ETH",
    "floorPrice": "3.5  ETH",
    "items": "350",
    "owners": "345"
  },
  {
    "volumeChange": "+24.2%",
    "floorChange": "+20.1%",
    "collection": "y00ts",
    "volume": "57.26  ETH",
    "floorPrice": "0.525  ETH",
    "items": "11.4K",
    "owners": "4.5K"
  },
  {
    "volumeChange": "",
    "floorChange": "",
    "collection": "Terraforms by Mathcastles",
    "volume": "55  ETH",
    "floorPrice": "1.46  ETH",
    "items": "9.9K",
    "owners": "2K"
  },
  {
    "volumeChange": "-67.6%",
    "floorChange": "-0%",
    "collection": "Milady Maker",
    "volume": "53.54  ETH",
    "floorPrice": "2.75  ETH",
    "items": "10K",
    "owners": "3.7K"
  },
  {
    "volumeChange": "-46.7%",
    "floorChange": "-0%",
    "collection": "Pixelmon - Generation 1",
    "volume": "53.23  ETH",
    "floorPrice": "2  ETH",
    "items": "12.1K",
    "owners": "2.7K"
  },
  {
    "volumeChange": "+125.2%",
    "floorChange": "-0.7%",
    "collection": "Otherdeed Expanded",
    "volume": "52.94  ETH",
    "floorPrice": "0.287  ETH",
    "items": "52.9K",
    "owners": "13.2K"
  },
  {
    "volumeChange": "",
    "floorChange": "",
    "collection": "Wrapped Cryptopunks",
    "volume": "52.16  ETH",
    "floorPrice": "129  ETH",
    "items": "838",
    "owners": "163"
  },
  {
    "volumeChange": "+7.1%",
    "floorChange": "-4.9%",
    "collection": "BlockGames Dice",
    "volume": "52  ETH",
    "floorPrice": "0.425  ETH",
    "items": "5.6K",
    "owners": "2K"
  },
  {
    "volumeChange": "-14.9%",
    "floorChange": "-1.5%",
    "collection": "CloneX",
    "volume": "48.77  ETH",
    "floorPrice": "1.249  ETH",
    "items": "19.5K",
    "owners": "10.1K"
  },
  {
    "volumeChange": "",
    "floorChange": "",
    "collection": "Fidenza by Tyler Hobbs",
    "volume": "47.64  ETH",
    "floorPrice": "59.88  ETH",
    "items": "999",
    "owners": "484"
  },
  {
    "volumeChange": "-27.1%",
    "floorChange": "+2.8%",
    "collection": "ElectricSheep",
    "volume": "44.95  ETH",
    "floorPrice": "1.85  ETH",
    "items": "7K",
    "owners": "2.3K"
  },
  {
    "volumeChange": "-30.9%",
    "floorChange": "-16%",
    "collection": "Pioneer of Fusionist",
    "volume": "43.84  ETH",
    "floorPrice": "3.4  ETH",
    "items": "298",
    "owners": "240"
  },
  {
    "volumeChange": "-82.3%",
    "floorChange": "+12.9%",
    "collection": "Skyborne - Nexian Gems",
    "volume": "39.83  ETH",
    "floorPrice": "0.79  ETH",
    "items": "3.3K",
    "owners": "994"
  },
  {
    "volumeChange": "",
    "floorChange": "",
    "collection": "Seedworld Vanguards",
    "volume": "38.49  ETH",
    "floorPrice": "0.48  ETH",
    "items": "4.4K",
    "owners": "1.1K"
  },
  {
    "volumeChange": "+69.5%",
    "floorChange": "+2.9%",
    "collection": "Yakuza Pandas",
    "volume": "38.36  ETH",
    "floorPrice": "1.8  ETH",
    "items": "7.9K",
    "owners": "2.3K"
  },
  {
    "volumeChange": "+16%",
    "floorChange": "-2.7%",
    "collection": "Opepen Edition",
    "volume": "37.9  ETH",
    "floorPrice": "0.389  ETH",
    "items": "16K",
    "owners": "4.6K"
  },
  {
    "volumeChange": "-44.3%",
    "floorChange": "-0%",
    "collection": "BoredApeKennelClub",
    "volume": "37.02  ETH",
    "floorPrice": "1.62  ETH",
    "items": "9.6K",
    "owners": "5.2K"
  },
  {
    "volumeChange": "+20%",
    "floorChange": "-3.1%",
    "collection": "Otherside Koda",
    "volume": "36.96  ETH",
    "floorPrice": "4.3  ETH",
    "items": "6.5K",
    "owners": "3.5K"
  },
  {
    "volumeChange": "+1,037.1%",
    "floorChange": "+3.1%",
    "collection": "The Grapes",
    "volume": "34.96  ETH",
    "floorPrice": "2  ETH",
    "items": "3.3K",
    "owners": "1.1K"
  },
  {
    "volumeChange": "-49%",
    "floorChange": "-0.4%",
    "collection": "Yogapetz",
    "volume": "34.51  ETH",
    "floorPrice": "0.667  ETH",
    "items": "10.1K",
    "owners": "3.3K"
  },
  {
    "volumeChange": "-20.1%",
    "floorChange": "-3%",
    "collection": "Mocaverse",
    "volume": "31.38  ETH",
    "floorPrice": "3.2  ETH",
    "items": "8.9K",
    "owners": "2.1K"
  },
  {
    "volumeChange": "+65.9%",
    "floorChange": "-1.4%",
    "collection": "Mittaria Genesis",
    "volume": "29.82  ETH",
    "floorPrice": "0.7  ETH",
    "items": "2.2K",
    "owners": "1.1K"
  },
  {
    "volumeChange": "-36.6%",
    "floorChange": "-2.2%",
    "collection": "Farm Land by Pixels",
    "volume": "23.65  ETH",
    "floorPrice": "1.59  ETH",
    "items": "5K",
    "owners": "2.1K"
  },
  {
    "volumeChange": "-62.2%",
    "floorChange": "-29.6%",
    "collection": "KOKODI",
    "volume": "23.58  ETH",
    "floorPrice": "0.095  ETH",
    "items": "5.5K",
    "owners": "1.7K"
  },
  {
    "volumeChange": "",
    "floorChange": "",
    "collection": "KartParty-YKZ",
    "volume": "22.64  ETH",
    "floorPrice": "2.3  ETH",
    "items": "699",
    "owners": "247"
  },
  {
    "volumeChange": "-78.3%",
    "floorChange": "+0.1%",
    "collection": "Doodles",
    "volume": "22.49  ETH",
    "floorPrice": "1.9  ETH",
    "items": "10K",
    "owners": "5.8K"
  },
  {
    "volumeChange": "+19.9%",
    "floorChange": "-0.3%",
    "collection": "V1 Cryptopunks (Wrapped)",
    "volume": "22.26  ETH",
    "floorPrice": "3.98  ETH",
    "items": "4.9K",
    "owners": "1K"
  },
  {
    "volumeChange": "-56.3%",
    "floorChange": "+23.5%",
    "collection": "SERAPH Priority Pass Official",
    "volume": "21.56  ETH",
    "floorPrice": "2.84  ETH",
    "items": "999",
    "owners": "446"
  },
  {
    "volumeChange": "-38.2%",
    "floorChange": "+9.6%",
    "collection": "Azuki Elementals",
    "volume": "21.55  ETH",
    "floorPrice": "0.587  ETH",
    "items": "14.5K",
    "owners": "5.1K"
  },
  {
    "volumeChange": "",
    "floorChange": "",
    "collection": "Memories of Qilin by Emily Xie",
    "volume": "21.32  ETH",
    "floorPrice": "4.99  ETH",
    "items": "1K",
    "owners": "514"
  },
  {
    "volumeChange": "",
    "floorChange": "",
    "collection": "Winds of Yawanawa by Yawanawa and Refik Anadol",
    "volume": "20.65  ETH",
    "floorPrice": "7.65  ETH",
    "items": "1K",
    "owners": "621"
  },
  {
    "volumeChange": "+400.3%",
    "floorChange": "+38.5%",
    "collection": "Purr Pass",
    "volume": "20.39  ETH",
    "floorPrice": "5.4  ETH",
    "items": "111",
    "owners": "104"
  },
  {
    "volumeChange": "+114.5%",
    "floorChange": "+68.4%",
    "collection": "Metacene Apostle NFT",
    "volume": "20.16  ETH",
    "floorPrice": "0.99  ETH",
    "items": "500",
    "owners": "319"
  },
  {
    "volumeChange": "+95%",
    "floorChange": "+3.7%",
    "collection": "Oh Ottie!",
    "volume": "20.16  ETH",
    "floorPrice": "1.347  ETH",
    "items": "2K",
    "owners": "1.3K"
  },
  {
    "volumeChange": "+561.4%",
    "floorChange": "+36.3%",
    "collection": "PORSCHΞ 911",
    "volume": "19.87  ETH",
    "floorPrice": "0.749  ETH",
    "items": "2.4K",
    "owners": "1.4K"
  },
  {
    "volumeChange": "",
    "floorChange": "",
    "collection": "Otherdeed",
    "volume": "19.45  ETH",
    "floorPrice": "0.55  ETH",
    "items": "84K",
    "owners": "17.1K"
  },
  {
    "volumeChange": "-11.2%",
    "floorChange": "+0.1%",
    "collection": "Cool Cats",
    "volume": "18.91  ETH",
    "floorPrice": "1  ETH",
    "items": "10K",
    "owners": "5.9K"
  },
  {
    "volumeChange": "",
    "floorChange": "",
    "collection": "YouAreTheChampion",
    "volume": "18.7  ETH",
    "floorPrice": "25  ETH",
    "items": "520",
    "owners": "212"
  },
  {
    "volumeChange": "+1,566.2%",
    "floorChange": "+75%",
    "collection": "Common Wealth Genesis NFT Series 1",
    "volume": "17.93  ETH",
    "floorPrice": "1.89  ETH",
    "items": "1.8K",
    "owners": "46"
  },
  {
    "volumeChange": "+7.1%",
    "floorChange": "-0%",
    "collection": "Neo Tokyo Outer Citizen V2",
    "volume": "17.47  ETH",
    "floorPrice": "2.75  ETH",
    "items": "3.2K",
    "owners": "1.2K"
  },
  {
    "volumeChange": "+24.2%",
    "floorChange": "+24%",
    "collection": "World Of Women",
    "volume": "16.96  ETH",
    "floorPrice": "1.444  ETH",
    "items": "10K",
    "owners": "5.4K"
  },
  {
    "volumeChange": "+887.5%",
    "floorChange": "+14.9%",
    "collection": "Mavia Land",
    "volume": "16.86  ETH",
    "floorPrice": "0.678  ETH",
    "items": "10K",
    "owners": "2.4K"
  },
  {
    "volumeChange": "+311.2%",
    "floorChange": "-2.3%",
    "collection": "mfer",
    "volume": "16.84  ETH",
    "floorPrice": "0.628  ETH",
    "items": "10K",
    "owners": "5.8K"
  },
  {
    "volumeChange": "",
    "floorChange": "",
    "collection": "THE WHITE RABBIT",
    "volume": "16.41  ETH",
    "floorPrice": "0.012  ETH",
    "items": "118",
    "owners": "203"
  },
  {
    "volumeChange": "-0.9%",
    "floorChange": "-8.4%",
    "collection": "Fortune Founder\u0027s Key by AOFverse",
    "volume": "16.24  ETH",
    "floorPrice": "0.435  ETH",
    "items": "2.2K",
    "owners": "1K"
  },
  {
    "volumeChange": "+210.3%",
    "floorChange": "-2.7%",
    "collection": "DeepBlack",
    "volume": "15.33  ETH",
    "floorPrice": "1.08  ETH",
    "items": "3.1K",
    "owners": "707"
  },
  {
    "volumeChange": "+131%",
    "floorChange": "+32.2%",
    "collection": "Skyborne - Genesis Immortals",
    "volume": "15.15  ETH",
    "floorPrice": "0.115  ETH",
    "items": "10K",
    "owners": "1.7K"
  },
  {
    "volumeChange": "",
    "floorChange": "",
    "collection": "Work X Genesis NFT",
    "volume": "14.69  ETH",
    "floorPrice": "0.09  ETH",
    "items": "653",
    "owners": "481"
  },
  {
    "volumeChange": "+80.1%",
    "floorChange": "-10%",
    "collection": "TOPIA Worlds",
    "volume": "14.3  ETH",
    "floorPrice": "2.7  ETH",
    "items": "10K",
    "owners": "1.4K"
  },
  {
    "volumeChange": "-32.6%",
    "floorChange": "+0.3%",
    "collection": "Neo Tokyo Citizen V2",
    "volume": "13.9  ETH",
    "floorPrice": "16  ETH",
    "items": "1.9K",
    "owners": "372"
  },
  {
    "volumeChange": "+90%",
    "floorChange": "+7.4%",
    "collection": "OnChainMonkey",
    "volume": "13.46  ETH",
    "floorPrice": "1.589  ETH",
    "items": "9.5K",
    "owners": "5.4K"
  },
  {
    "volumeChange": "+290.4%",
    "floorChange": "+5.5%",
    "collection": "The Harvest by Per Kristian Stoveland",
    "volume": "13.4  ETH",
    "floorPrice": "4.16  ETH",
    "items": "400",
    "owners": "269"
  },
  {
    "volumeChange": "-40.9%",
    "floorChange": "-1.3%",
    "collection": "BEANZ Official",
    "volume": "13.13  ETH",
    "floorPrice": "0.395  ETH",
    "items": "19.9K",
    "owners": "8K"
  },
  {
    "volumeChange": "+957.1%",
    "floorChange": "+74%",
    "collection": "Nifty Island: Legendary Palms",
    "volume": "12.54  ETH",
    "floorPrice": "0.785  ETH",
    "items": "6",
    "owners": "529"
  },
  {
    "volumeChange": "+149.2%",
    "floorChange": "-22.2%",
    "collection": "IconicNFT",
    "volume": "12.33  ETH",
    "floorPrice": "0.389  ETH",
    "items": "400",
    "owners": "144"
  },
  {
    "volumeChange": "+1.9%",
    "floorChange": "-0.1%",
    "collection": "Nakamigos",
    "volume": "12.1  ETH",
    "floorPrice": "0.172  ETH",
    "items": "20K",
    "owners": "5.6K"
  },
  {
    "volumeChange": "+25.7%",
    "floorChange": "+10.5%",
    "collection": "Pudgy Rods",
    "volume": "11.99  ETH",
    "floorPrice": "0.55  ETH",
    "items": "7.4K",
    "owners": "2.9K"
  },
  {
    "volumeChange": "+62.1%",
    "floorChange": "-9.3%",
    "collection": "Imaginary Ones",
    "volume": "11.67  ETH",
    "floorPrice": "1.02  ETH",
    "items": "8.9K",
    "owners": "1.4K"
  },
  {
    "volumeChange": "-59%",
    "floorChange": "-1.9%",
    "collection": "Meebits",
    "volume": "11.5  ETH",
    "floorPrice": "1.16  ETH",
    "items": "20K",
    "owners": "6.7K"
  },
  {
    "volumeChange": "+34.2%",
    "floorChange": "-2.7%",
    "collection": "Chromie Squiggle by Snowfro",
    "volume": "11.29  ETH",
    "floorPrice": "8.75  ETH",
    "items": "10K",
    "owners": "2.9K"
  },
  {
    "volumeChange": "",
    "floorChange": "",
    "collection": "Hedz",
    "volume": "11.25  ETH",
    "floorPrice": "1.98  ETH",
    "items": "1K",
    "owners": "305"
  },
  {
    "volumeChange": "+422.6%",
    "floorChange": "-7.6%",
    "collection": "PROOF Collective",
    "volume": "11.21  ETH",
    "floorPrice": "2.4  ETH",
    "items": "1K",
    "owners": "916"
  },
  {
    "volumeChange": "+897.4%",
    "floorChange": "+37.1%",
    "collection": "Gray Boys",
    "volume": "11.21  ETH",
    "floorPrice": "0.139  ETH",
    "items": "10K",
    "owners": "3.4K"
  },
  {
    "volumeChange": "+386%",
    "floorChange": "-3.8%",
    "collection": "The Memes by 6529",
    "volume": "10.9  ETH",
    "floorPrice": "0.025  ETH",
    "items": "180",
    "owners": "9.7K"
  },
  {
    "volumeChange": "-60.4%",
    "floorChange": "-0.7%",
    "collection": "Azuki Elemental Beans",
    "volume": "10.43  ETH",
    "floorPrice": "0.704  ETH",
    "items": "5.4K",
    "owners": "1.9K"
  },
  {
    "volumeChange": "+217.1%",
    "floorChange": "-25%",
    "collection": "Town Star",
    "volume": "10.38  ETH",
    "floorPrice": "~0.001  ETH",
    "items": "1.9K",
    "owners": "69.6K"
  },
  {
    "volumeChange": "",
    "floorChange": "",
    "collection": "Kitaro World",
    "volume": "10.31  ETH",
    "floorPrice": "0.16  ETH",
    "items": "7.8K",
    "owners": "2.2K"
  },
  {
    "volumeChange": "+321.2%",
    "floorChange": "-1.3%",
    "collection": "TheCurrency",
    "volume": "10.29  ETH",
    "floorPrice": "1.579  ETH",
    "items": "2K",
    "owners": "1.6K"
  },
  {
    "volumeChange": "-59.1%",
    "floorChange": "-2.5%",
    "collection": "Parallel Planetfall",
    "volume": "9.65  ETH",
    "floorPrice": "0.003  ETH",
    "items": "558",
    "owners": "1.7K"
  },
  {
    "volumeChange": "+108.6%",
    "floorChange": "+1.8%",
    "collection": "UA3 The Real OG Pass",
    "volume": "9.55  ETH",
    "floorPrice": "4.99  ETH",
    "items": "1",
    "owners": "299"
  },
  {
    "volumeChange": "-40.4%",
    "floorChange": "-1.8%",
    "collection": "Sappy Seals",
    "volume": "9.398  ETH",
    "floorPrice": "0.632  ETH",
    "items": "10K",
    "owners": "2.1K"
  },
  {
    "volumeChange": "+71.9%",
    "floorChange": "+7.8%",
    "collection": "Egg",
    "volume": "9.369  ETH",
    "floorPrice": "0.29  ETH",
    "items": "16.7K",
    "owners": "6.8K"
  },
  {
    "volumeChange": "",
    "floorChange": "",
    "collection": "Candy Collective: Genesis Collection",
    "volume": "9.115  ETH",
    "floorPrice": "0.34  ETH",
    "items": "2K",
    "owners": "655"
  },
  {
    "volumeChange": "",
    "floorChange": "",
    "collection": "PROOF Collective Grails",
    "volume": "9.066  ETH",
    "floorPrice": "0.769  ETH",
    "items": "1K",
    "owners": "648"
  },
  {
    "volumeChange": "-14.3%",
    "floorChange": "-10%",
    "collection": "Trademark by Jack Butcher",
    "volume": "9.002  ETH",
    "floorPrice": "0.125  ETH",
    "items": "10K",
    "owners": "3.7K"
  },
  {
    "volumeChange": "-63.5%",
    "floorChange": "-12.9%",
    "collection": "a KID called BEAST",
    "volume": "8.999  ETH",
    "floorPrice": "0.278  ETH",
    "items": "10K",
    "owners": "3.9K"
  },
  {
    "volumeChange": "",
    "floorChange": "",
    "collection": "Memories of Digital Data by Kazuhiro Tanimoto",
    "volume": "8.989  ETH",
    "floorPrice": "0.78  ETH",
    "items": "450",
    "owners": "239"
  },
  {
    "volumeChange": "+9.7%",
    "floorChange": "-4.8%",
    "collection": "ChronoForge",
    "volume": "8.778  ETH",
    "floorPrice": "0.26  ETH",
    "items": "7.5K",
    "owners": "1.5K"
  },
  {
    "volumeChange": "",
    "floorChange": "",
    "collection": "Meridian by Matt DesLauriers",
    "volume": "8.5  ETH",
    "floorPrice": "8.69  ETH",
    "items": "1K",
    "owners": "627"
  },
  {
    "volumeChange": "",
    "floorChange": "",
    "collection": "DigiDaigaku Genesis",
    "volume": "8.425  ETH",
    "floorPrice": "4.88  ETH",
    "items": "2K",
    "owners": "755"
  },
  {
    "volumeChange": "+16.8%",
    "floorChange": "-5.5%",
    "collection": "Cryptoadz",
    "volume": "8.386  ETH",
    "floorPrice": "0.86  ETH",
    "items": "7K",
    "owners": "4K"
  },
  {
    "volumeChange": "-46.3%",
    "floorChange": "+7.1%",
    "collection": "Parallel Avatars",
    "volume": "8.319  ETH",
    "floorPrice": "1.069  ETH",
    "items": "11K",
    "owners": "2.2K"
  },
  {
    "volumeChange": "",
    "floorChange": "",
    "collection": "Flyfish Club",
    "volume": "8.318  ETH",
    "floorPrice": "1.478  ETH",
    "items": "3K",
    "owners": "1.3K"
  },
  {
    "volumeChange": "+31.8%",
    "floorChange": "+10.1%",
    "collection": "Genuine Undead",
    "volume": "8.305  ETH",
    "floorPrice": "0.11  ETH",
    "items": "10K",
    "owners": "3.1K"
  },
  {
    "volumeChange": "-74.6%",
    "floorChange": "+14.6%",
    "collection": "Checks — Originals",
    "volume": "8.002  ETH",
    "floorPrice": "0.286  ETH",
    "items": "5.7K",
    "owners": "1.9K"
  },
  {
    "volumeChange": "",
    "floorChange": "",
    "collection": "parallel",
    "volume": "7.983  ETH",
    "floorPrice": "~0.001  ETH",
    "items": "989",
    "owners": "60.7K"
  },
  {
    "volumeChange": "-45.2%",
    "floorChange": "+29.4%",
    "collection": "NFTrees",
    "volume": "7.8  ETH",
    "floorPrice": "11  ETH",
    "items": "420",
    "owners": "250"
  },
  {
    "volumeChange": "-48.2%",
    "floorChange": "-9.9%",
    "collection": "Checks — Edition",
    "volume": "7.759  ETH",
    "floorPrice": "0.531  ETH",
    "items": "5.4K",
    "owners": "3K"
  },
  {
    "volumeChange": "",
    "floorChange": "",
    "collection": "Treeverse",
    "volume": "7.716  ETH",
    "floorPrice": "0.705  ETH",
    "items": "10.4K",
    "owners": "3.3K"
  },
  {
    "volumeChange": "+160.8%",
    "floorChange": "-6%",
    "collection": "AcclimatedMoonCats",
    "volume": "7.658  ETH",
    "floorPrice": "0.225  ETH",
    "items": "19.8K",
    "owners": "5.7K"
  },
  {
    "volumeChange": "+310.8%",
    "floorChange": "-0%",
    "collection": "Worried Meerkats",
    "volume": "7.634  ETH",
    "floorPrice": "0.489  ETH",
    "items": "1.1K",
    "owners": "275"
  },
  {
    "volumeChange": "-60.3%",
    "floorChange": "+6.2%",
    "collection": "Shrapnel Operators Collection",
    "volume": "7.436  ETH",
    "floorPrice": "0.274  ETH",
    "items": "10K",
    "owners": "3K"
  },
  {
    "volumeChange": "",
    "floorChange": "",
    "collection": "Tribe Diamonds",
    "volume": "7.273  ETH",
    "floorPrice": "9  ETH",
    "items": "200",
    "owners": "112"
  },
  {
    "volumeChange": "",
    "floorChange": "",
    "collection": "504.xyz",
    "volume": "7.27  ETH",
    "floorPrice": "1.8  ETH",
    "items": "268",
    "owners": "173"
  },
  {
    "volumeChange": "",
    "floorChange": "",
    "collection": "ENS domains",
    "volume": "7.263  ETH",
    "floorPrice": "~0.001  ETH",
    "items": "3.2M",
    "owners": "712.5K"
  },
  {
    "volumeChange": "+380.4%",
    "floorChange": "+7.6%",
    "collection": "alignDRAW",
    "volume": "7.48  ETH",
    "floorPrice": "0.199  ETH",
    "items": "2.7K",
    "owners": "500"
  },
  {
    "volumeChange": "-54.4%",
    "floorChange": "-1.2%",
    "collection": "Impostors Genesis Aliens",
    "volume": "6.853  ETH",
    "floorPrice": "0.68  ETH",
    "items": "10.4K",
    "owners": "4.3K"
  },
  {
    "volumeChange": "",
    "floorChange": "",
    "collection": "Sybil Samurai",
    "volume": "6.665  ETH",
    "floorPrice": "0.105  ETH",
    "items": "5.1K",
    "owners": "1.3K"
  },
  {
    "volumeChange": "-70.3%",
    "floorChange": "-6%",
    "collection": "Matr1x 2061",
    "volume": "6.3  ETH",
    "floorPrice": "3.1  ETH",
    "items": "2.1K",
    "owners": "643"
  },
  {
    "volumeChange": "",
    "floorChange": "",
    "collection": "Land of Valeria",
    "volume": "6.223  ETH",
    "floorPrice": "0.9  ETH",
    "items": "10K",
    "owners": "1.7K"
  },
  {
    "volumeChange": "+91.2%",
    "floorChange": "+19.5%",
    "collection": "Invisible Friends",
    "volume": "6.133  ETH",
    "floorPrice": "0.448  ETH",
    "items": "5K",
    "owners": "3.6K"
  },
  {
    "volumeChange": "",
    "floorChange": "",
    "collection": "The Mounts of Seedworld",
    "volume": "6.022  ETH",
    "floorPrice": "0.48  ETH",
    "items": "3.1K",
    "owners": "1.3K"
  },
  {
    "volumeChange": "",
    "floorChange": "",
    "collection": "FRESH HELL",
    "volume": "5.993  ETH",
    "floorPrice": "6.66  ETH",
    "items": "2",
    "owners": "61"
  },
  {
    "volumeChange": "+165.3%",
    "floorChange": "-6.3%",
    "collection": "Vendetta Frontier Pass",
    "volume": "5.812  ETH",
    "floorPrice": "0.28  ETH",
    "items": "888",
    "owners": "424"
  },
  {
    "volumeChange": "",
    "floorChange": "",
    "collection": "AlfaDAO",
    "volume": "5.5  ETH",
    "floorPrice": "3  ETH",
    "items": "502",
    "owners": "435"
  },
  {
    "volumeChange": "",
    "floorChange": "",
    "collection": "Rare Pepe (2016 - 2018)",
    "volume": "5.323  ETH",
    "floorPrice": "0.015  ETH",
    "items": "1.6K",
    "owners": "5K"
  },
  {
    "volumeChange": "",
    "floorChange": "",
    "collection": "Steady Stack Legends",
    "volume": "5.264  ETH",
    "floorPrice": "0.29  ETH",
    "items": "10K",
    "owners": "2.8K"
  },
  {
    "volumeChange": "",
    "floorChange": "",
    "collection": "MEMBERSHIP S",
    "volume": "5.165  ETH",
    "floorPrice": "3  ETH",
    "items": "391",
    "owners": "335"
  },
  {
    "volumeChange": "+2,496%",
    "floorChange": "+9.1%",
    "collection": "Nakamigos-CLOAKS",
    "volume": "5.144  ETH",
    "floorPrice": "0.029  ETH",
    "items": "20K",
    "owners": "3.9K"
  },
  {
    "volumeChange": "",
    "floorChange": "",
    "collection": "Memewhales by tradeAI",
    "volume": "5.104  ETH",
    "floorPrice": "3.75  ETH",
    "items": "700",
    "owners": "482"
  },
  {
    "volumeChange": "",
    "floorChange": "",
    "collection": "MetaHero Universe: Planet Tokens",
    "volume": "5.079  ETH",
    "floorPrice": "0.043  ETH",
    "items": "11",
    "owners": "10.3K"
  },
  {
    "volumeChange": "-84.9%",
    "floorChange": "-0.5%",
    "collection": "L3E7 Worlds",
    "volume": "4.97  ETH",
    "floorPrice": "5.994  ETH",
    "items": "600",
    "owners": "361"
  },
  {
    "volumeChange": "",
    "floorChange": "",
    "collection": "Nexus Gaming Lifetime Pass",
    "volume": "4.91  ETH",
    "floorPrice": "1.7  ETH",
    "items": "2.1K",
    "owners": "523"
  },
  {
    "volumeChange": "",
    "floorChange": "",
    "collection": "Consortium Key",
    "volume": "4.862  ETH",
    "floorPrice": "1.2  ETH",
    "items": "777",
    "owners": "578"
  },
  {
    "volumeChange": "+401.7%",
    "floorChange": "+5.3%",
    "collection": "Defimons Apartments",
    "volume": "4.859  ETH",
    "floorPrice": "0.34  ETH",
    "items": "2.9K",
    "owners": "790"
  },
  {
    "volumeChange": "+1,116%",
    "floorChange": "-3.7%",
    "collection": "Akutars",
    "volume": "4.805  ETH",
    "floorPrice": "0.079  ETH",
    "items": "15K",
    "owners": "5K"
  },
  {
    "volumeChange": "",
    "floorChange": "",
    "collection": "LaserCat",
    "volume": "4.79  ETH",
    "floorPrice": "5.7  ETH",
    "items": "520",
    "owners": "73"
  },
  {
    "volumeChange": "-51%",
    "floorChange": "-7%",
    "collection": "Potatoz",
    "volume": "4.785  ETH",
    "floorPrice": "1.6  ETH",
    "items": "10K",
    "owners": "3K"
  },
  {
    "volumeChange": "+388.2%",
    "floorChange": "+15.8%",
    "collection": "Supreme Kong",
    "volume": "4.78  ETH",
    "floorPrice": "0.585  ETH",
    "items": "2K",
    "owners": "495"
  },
  {
    "volumeChange": "-33%",
    "floorChange": "+4.1%",
    "collection": "Sproto Gremlins",
    "volume": "4.696  ETH",
    "floorPrice": "0.583  ETH",
    "items": "3.3K",
    "owners": "1.2K"
  },
  {
    "volumeChange": "",
    "floorChange": "",
    "collection": "On the Edge of Oblivion",
    "volume": "4.65  ETH",
    "floorPrice": "2.99  ETH",
    "items": "554",
    "owners": "71"
  },
  {
    "volumeChange": "-38.4%",
    "floorChange": "-0.7%",
    "collection": "Bit Bears",
    "volume": "4.565  ETH",
    "floorPrice": "2.48  ETH",
    "items": "2.3K",
    "owners": "935"
  },
  {
    "volumeChange": "-53.6%",
    "floorChange": "+7.7%",
    "collection": "Descendants of Smurfcat",
    "volume": "4.515  ETH",
    "floorPrice": "0.14  ETH",
    "items": "3.3K",
    "owners": "1.7K"
  },
  {
    "volumeChange": "+306.4%",
    "floorChange": "+0.7%",
    "collection": "FLUF",
    "volume": "4.452  ETH",
    "floorPrice": "0.899  ETH",
    "items": "10K",
    "owners": "3.3K"
  },
  {
    "volumeChange": "-85.2%",
    "floorChange": "+1.5%",
    "collection": "Grails V",
    "volume": "4.419  ETH",
    "floorPrice": "0.203  ETH",
    "items": "785",
    "owners": "506"
  },
  {
    "volumeChange": "+18.9%",
    "floorChange": "-24.5%",
    "collection": "Worldwide Webb Land",
    "volume": "4.374  ETH",
    "floorPrice": "0.15  ETH",
    "items": "9.5K",
    "owners": "4K"
  },
  {
    "volumeChange": "",
    "floorChange": "",
    "collection": "Azuki Apes",
    "volume": "4.223  ETH",
    "floorPrice": "0.047  ETH",
    "items": "1.4K",
    "owners": "288"
  },
  {
    "volumeChange": "+1,297.5%",
    "floorChange": "+103.3%",
    "collection": "PROOF Pass",
    "volume": "4.175  ETH",
    "floorPrice": "0.61  ETH",
    "items": "222",
    "owners": "198"
  },
  {
    "volumeChange": "",
    "floorChange": "",
    "collection": "Chosen of Civitas",
    "volume": "4.127  ETH",
    "floorPrice": "0.163  ETH",
    "items": "1.5K",
    "owners": "648"
  },
  {
    "volumeChange": "",
    "floorChange": "",
    "collection": "Common Wealth Genesis NFT Series 2",
    "volume": "4.113  ETH",
    "floorPrice": "0.5  ETH",
    "items": "3.4K",
    "owners": "231"
  },
  {
    "volumeChange": "+18.9%",
    "floorChange": "-0.2%",
    "collection": "Sofa Vision",
    "volume": "4.061  ETH",
    "floorPrice": "0.073  ETH",
    "items": "4.4K",
    "owners": "1.2K"
  },
  {
    "volumeChange": "-8.3%",
    "floorChange": "-5%",
    "collection": "HV-MTL",
    "volume": "4.059  ETH",
    "floorPrice": "0.199  ETH",
    "items": "28.3K",
    "owners": "9.2K"
  },
  {
    "volumeChange": "-85.1%",
    "floorChange": "-20.3%",
    "collection": "Quirkies",
    "volume": "4.047  ETH",
    "floorPrice": "0.55  ETH",
    "items": "5K",
    "owners": "1.7K"
  },
  {
    "volumeChange": "-48.6%",
    "floorChange": "+20%",
    "collection": "AltLayer OG Badge",
    "volume": "4  ETH",
    "floorPrice": "4.8  ETH",
    "items": "400",
    "owners": "299"
  },
  {
    "volumeChange": "+353.9%",
    "floorChange": "-10.7%",
    "collection": "Binary",
    "volume": "3.981  ETH",
    "floorPrice": "0.05  ETH",
    "items": "7.1K",
    "owners": "1.7K"
  },
  {
    "volumeChange": "+116.7%",
    "floorChange": "-1.9%",
    "collection": "Realms (for Adventurers)",
    "volume": "3.978  ETH",
    "floorPrice": "0.52  ETH",
    "items": "8K",
    "owners": "485"
  },
  {
    "volumeChange": "-52.3%",
    "floorChange": "-3.5%",
    "collection": "Keepers V2",
    "volume": "3.943  ETH",
    "floorPrice": "0.14  ETH",
    "items": "10K",
    "owners": "2.6K"
  },
  {
    "volumeChange": "",
    "floorChange": "",
    "collection": "OpenSea Shared Storefront",
    "volume": "3.878  ETH",
    "floorPrice": "0  ETH",
    "items": "2.1M",
    "owners": "727.6K"
  },
  {
    "volumeChange": "-78.7%",
    "floorChange": "-25.9%",
    "collection": "The Ant Republic",
    "volume": "3.798  ETH",
    "floorPrice": "0.02  ETH",
    "items": "4.5K",
    "owners": "1.4K"
  },
  {
    "volumeChange": "",
    "floorChange": "",
    "collection": "Travel Tiger Club",
    "volume": "3.789  ETH",
    "floorPrice": "4  ETH",
    "items": "1K",
    "owners": "697"
  },
  {
    "volumeChange": "+124%",
    "floorChange": "-16.7%",
    "collection": "Wanderers - RAM Beta Bundle",
    "volume": "3.755  ETH",
    "floorPrice": "0.075  ETH",
    "items": "2.2K",
    "owners": "805"
  },
  {
    "volumeChange": "+34.5%",
    "floorChange": "-0.6%",
    "collection": "My Pet Hooligan",
    "volume": "3.735  ETH",
    "floorPrice": "0.92  ETH",
    "items": "8.9K",
    "owners": "3.8K"
  },
  {
    "volumeChange": "+759.8%",
    "floorChange": "+2.3%",
    "collection": "Mutant Hounds",
    "volume": "3.71  ETH",
    "floorPrice": "0.133  ETH",
    "items": "7.4K",
    "owners": "2.2K"
  },
  {
    "volumeChange": "",
    "floorChange": "",
    "collection": "Land",
    "volume": "3.65  ETH",
    "floorPrice": "0.034  ETH",
    "items": "20K",
    "owners": "3.5K"
  },
  {
    "volumeChange": "",
    "floorChange": "",
    "collection": "Dour Darcels",
    "volume": "3.636  ETH",
    "floorPrice": "0.034  ETH",
    "items": "10K",
    "owners": "4.3K"
  },
  {
    "volumeChange": "+57.5%",
    "floorChange": "-0.9%",
    "collection": "RENGA",
    "volume": "3.612  ETH",
    "floorPrice": "0.217  ETH",
    "items": "8.9K",
    "owners": "3.2K"
  },
  {
    "volumeChange": "",
    "floorChange": "",
    "collection": "TradFiLines",
    "volume": "3.6  ETH",
    "floorPrice": "1.92  ETH",
    "items": "500",
    "owners": "137"
  },
  {
    "volumeChange": "-53.2%",
    "floorChange": "-2.3%",
    "collection": "Pirate",
    "volume": "3.55  ETH",
    "floorPrice": "0.379  ETH",
    "items": "10K",
    "owners": "2.7K"
  },
  {
    "volumeChange": "",
    "floorChange": "",
    "collection": "0N1 Force",
    "volume": "3.51  ETH",
    "floorPrice": "0.86  ETH",
    "items": "7.8K",
    "owners": "3.7K"
  },
  {
    "volumeChange": "",
    "floorChange": "",
    "collection": "OzDAO",
    "volume": "3.49  ETH",
    "floorPrice": "6.09  ETH",
    "items": "163",
    "owners": "162"
  },
  {
    "volumeChange": "+20.5%",
    "floorChange": "+9.3%",
    "collection": "DegenToonz",
    "volume": "3.441  ETH",
    "floorPrice": "0.163  ETH",
    "items": "8.9K",
    "owners": "3.7K"
  },
  {
    "volumeChange": "+700.7%",
    "floorChange": "+8.9%",
    "collection": "Generativemasks",
    "volume": "3.419  ETH",
    "floorPrice": "0.048  ETH",
    "items": "10K",
    "owners": "3.2K"
  },
  {
    "volumeChange": "",
    "floorChange": "",
    "collection": "JEFFWorld Genesis Avatar",
    "volume": "3.34  ETH",
    "floorPrice": "0.01  ETH",
    "items": "5.1K",
    "owners": "676"
  },
  {
    "volumeChange": "-85.6%",
    "floorChange": "-17.5%",
    "collection": "Ether Avatar",
    "volume": "3.339  ETH",
    "floorPrice": "0.164  ETH",
    "items": "4.8K",
    "owners": "1.2K"
  },
  {
    "volumeChange": "",
    "floorChange": "",
    "collection": "Flightless Space Agency",
    "volume": "3.201  ETH",
    "floorPrice": "0.2  ETH",
    "items": "3K",
    "owners": "983"
  },
  {
    "volumeChange": "-22.3%",
    "floorChange": "-2.9%",
    "collection": "Otherside Vessels",
    "volume": "3.15  ETH",
    "floorPrice": "0.17  ETH",
    "items": "15.1K",
    "owners": "6.5K"
  },
  {
    "volumeChange": "",
    "floorChange": "",
    "collection": "Band Bears",
    "volume": "3.133  ETH",
    "floorPrice": "3.75  ETH",
    "items": "1.2K",
    "owners": "431"
  },
  {
    "volumeChange": "+99.6%",
    "floorChange": "-7.5%",
    "collection": "RTFKT SKIN VIAL: EVO X",
    "volume": "3.081  ETH",
    "floorPrice": "0.032  ETH",
    "items": "8.8K",
    "owners": "4.7K"
  },
  {
    "volumeChange": "+100%",
    "floorChange": "+0.7%",
    "collection": "Alpha Gate - Space Nation",
    "volume": "2.93  ETH",
    "floorPrice": "1.51  ETH",
    "items": "515",
    "owners": "438"
  },
  {
    "volumeChange": "",
    "floorChange": "",
    "collection": "FLUF World: Burrows",
    "volume": "2.868  ETH",
    "floorPrice": "0.192  ETH",
    "items": "10.5K",
    "owners": "3.2K"
  },
  {
    "volumeChange": "+40.9%",
    "floorChange": "-12.5%",
    "collection": "ChronoForge Support Airships",
    "volume": "2.816  ETH",
    "floorPrice": "0.245  ETH",
    "items": "2.5K",
    "owners": "424"
  },
  {
    "volumeChange": "",
    "floorChange": "",
    "collection": "RumbleKongLeague",
    "volume": "2.805  ETH",
    "floorPrice": "0.269  ETH",
    "items": "10K",
    "owners": "3K"
  },
  {
    "volumeChange": "+3.9%",
    "floorChange": "-2.3%",
    "collection": "The Plooshies",
    "volume": "2.794  ETH",
    "floorPrice": "0.42  ETH",
    "items": "3.3K",
    "owners": "583"
  },
  {
    "volumeChange": "",
    "floorChange": "",
    "collection": "Gener8tive K-Compositions",
    "volume": "2.75  ETH",
    "floorPrice": "6  ETH",
    "items": "250",
    "owners": "135"
  },
  {
    "volumeChange": "-49.7%",
    "floorChange": "+3%",
    "collection": "KFCdao pass",
    "volume": "2.74  ETH",
    "floorPrice": "1.37  ETH",
    "items": "163",
    "owners": "138"
  },
  {
    "volumeChange": "+694.5%",
    "floorChange": "+200%",
    "collection": "NiftyPistol",
    "volume": "2.732  ETH",
    "floorPrice": "0.096  ETH",
    "items": "3.8K",
    "owners": "1.9K"
  },
  {
    "volumeChange": "-12.6%",
    "floorChange": "-2.6%",
    "collection": "Michelin 3xplorer Club",
    "volume": "2.72  ETH",
    "floorPrice": "0.262  ETH",
    "items": "2.4K",
    "owners": "969"
  },
  {
    "volumeChange": "",
    "floorChange": "",
    "collection": "SAINTS of LA",
    "volume": "2.717  ETH",
    "floorPrice": "0.145  ETH",
    "items": "2.2K",
    "owners": "643"
  },
  {
    "volumeChange": "-49.1%",
    "floorChange": "+5.8%",
    "collection": "loomlocknft",
    "volume": "2.714  ETH",
    "floorPrice": "0.386  ETH",
    "items": "9.6K",
    "owners": "2.5K"
  },
  {
    "volumeChange": "",
    "floorChange": "",
    "collection": "MPL",
    "volume": "2.693  ETH",
    "floorPrice": "0.008  ETH",
    "items": "10K",
    "owners": "2.3K"
  },
  {
    "volumeChange": "-52.5%",
    "floorChange": "-0.4%",
    "collection": "KILLABEARS",
    "volume": "2.675  ETH",
    "floorPrice": "0.785  ETH",
    "items": "3.3K",
    "owners": "1.1K"
  },
  {
    "volumeChange": "+4.1%",
    "floorChange": "+8.4%",
    "collection": "Sofa Maker",
    "volume": "2.666  ETH",
    "floorPrice": "0.13  ETH",
    "items": "1.3K",
    "owners": "657"
  },
  {
    "volumeChange": "",
    "floorChange": "",
    "collection": "MetaTrustDAO",
    "volume": "2.649  ETH",
    "floorPrice": "0.088  ETH",
    "items": "5K",
    "owners": "446"
  },
  {
    "volumeChange": "+2.5%",
    "floorChange": "+2.4%",
    "collection": "Exosama",
    "volume": "2.579  ETH",
    "floorPrice": "0.299  ETH",
    "items": "10K",
    "owners": "1.4K"
  },
  {
    "volumeChange": "+56.6%",
    "floorChange": "-3.2%",
    "collection": "Karma",
    "volume": "2.547  ETH",
    "floorPrice": "0.15  ETH",
    "items": "12.7K",
    "owners": "2.8K"
  },
  {
    "volumeChange": "",
    "floorChange": "",
    "collection": "Dyad NFT",
    "volume": "2.451  ETH",
    "floorPrice": "0.4  ETH",
    "items": "468",
    "owners": "262"
  },
  {
    "volumeChange": "",
    "floorChange": "",
    "collection": "Convergence Pepe",
    "volume": "2.45  ETH",
    "floorPrice": "1.6  ETH",
    "items": "106",
    "owners": "80"
  },
  {
    "volumeChange": "",
    "floorChange": "",
    "collection": "ForgottenRunesWizardsCult",
    "volume": "2.441  ETH",
    "floorPrice": "0.834  ETH",
    "items": "9.3K",
    "owners": "3.1K"
  },
  {
    "volumeChange": "",
    "floorChange": "",
    "collection": "THE SECOND ASPECT OF THE NINE",
    "volume": "2.44  ETH",
    "floorPrice": "2.38  ETH",
    "items": "81",
    "owners": "72"
  },
  {
    "volumeChange": "-54.5%",
    "floorChange": "-1.1%",
    "collection": "Gutter Cat Gang",
    "volume": "2.422  ETH",
    "floorPrice": "0.445  ETH",
    "items": "3K",
    "owners": "1.7K"
  },
  {
    "volumeChange": "",
    "floorChange": "",
    "collection": "X MARKS THE SPOT",
    "volume": "2.395  ETH",
    "floorPrice": "1.399  ETH",
    "items": "100",
    "owners": "89"
  },
  {
    "volumeChange": "",
    "floorChange": "",
    "collection": "BrainDrops",
    "volume": "2.388  ETH",
    "floorPrice": "0.069  ETH",
    "items": "14.4K",
    "owners": "3.5K"
  },
  {
    "volumeChange": "",
    "floorChange": "",
    "collection": "Wilder World",
    "volume": "2.355  ETH",
    "floorPrice": "0.29  ETH",
    "items": "6.4K",
    "owners": "2.2K"
  },
  {
    "volumeChange": "+346.3%",
    "floorChange": "+19%",
    "collection": "Genesis Dimensional Stones",
    "volume": "2.311  ETH",
    "floorPrice": "0.309  ETH",
    "items": "1K",
    "owners": "298"
  },
  {
    "volumeChange": "+1,279.2%",
    "floorChange": "+20%",
    "collection": "HELIX Founder Pass",
    "volume": "2.398  ETH",
    "floorPrice": "0.12  ETH",
    "items": "5K",
    "owners": "903"
  },
  {
    "volumeChange": "",
    "floorChange": "",
    "collection": "Chimera by mpkoz",
    "volume": "2.305  ETH",
    "floorPrice": "0.99  ETH",
    "items": "987",
    "owners": "612"
  },
  {
    "volumeChange": "-72.2%",
    "floorChange": "-1%",
    "collection": "MetaHero",
    "volume": "2.284  ETH",
    "floorPrice": "0.389  ETH",
    "items": "8K",
    "owners": "2.4K"
  },
  {
    "volumeChange": "",
    "floorChange": "",
    "collection": "Friendship Bracelets by Alexis André",
    "volume": "2.258  ETH",
    "floorPrice": "0.075  ETH",
    "items": "38.7K",
    "owners": "12.1K"
  },
  {
    "volumeChange": "+79.5%",
    "floorChange": "-0.1%",
    "collection": "CyberBrokers",
    "volume": "2.253  ETH",
    "floorPrice": "0.269  ETH",
    "items": "10K",
    "owners": "3K"
  },
  {
    "volumeChange": "-78.8%",
    "floorChange": "+5.7%",
    "collection": "Signature by Jack Butcher",
    "volume": "2.2  ETH",
    "floorPrice": "2.79  ETH",
    "items": "200",
    "owners": "129"
  },
  {
    "volumeChange": "",
    "floorChange": "",
    "collection": "WADE F\u0026F",
    "volume": "2.189  ETH",
    "floorPrice": "1.1  ETH",
    "items": "2.1K",
    "owners": "792"
  },
  {
    "volumeChange": "-93.5%",
    "floorChange": "-14.3%",
    "collection": "Fusionist - Quartan Primes",
    "volume": "2.149  ETH",
    "floorPrice": "1.329  ETH",
    "items": "641",
    "owners": "394"
  }
]