[
  {
    "hashtag": "#rarible",
    "post": 30
  },
  {
    "hashtag": "#digitalart",
    "post": 12
  },
  {
    "hashtag": "#nftart",
    "post": 11
  },
  {
    "hashtag": "#nft",
    "post": 10
  },
  {
    "hashtag": "#nftcommunity",
    "post": 8
  },
  {
    "hashtag": "#nfts",
    "post": 7
  },
  {
    "hashtag": "#ufo",
    "post": 6
  },
  {
    "hashtag": "#ufotwitter",
    "post": 6
  },
  {
    "hashtag": "#value",
    "post": 6
  },
  {
    "hashtag": "#disclosure",
    "post": 6
  },
  {
    "hashtag": "#opensea",
    "post": 5
  },
  {
    "hashtag": "#nftsales",
    "post": 3
  },
  {
    "hashtag": "#nftcollector",
    "post": 3
  },
  {
    "hashtag": "#nftartist",
    "post": 3
  },
  {
    "hashtag": "#christmas",
    "post": 2
  },
  {
    "hashtag": "#nftartists",
    "post": 2
  },
  {
    "hashtag": "#buynfts",
    "post": 2
  },
  {
    "hashtag": "#openseanft",
    "post": 2
  },
  {
    "hashtag": "#openseacollection",
    "post": 2
  },
  {
    "hashtag": "#polygonnfts",
    "post": 2
  },
  {
    "hashtag": "#supporteachothers",
    "post": 2
  },
  {
    "hashtag": "#artist",
    "post": 2
  },
  {
    "hashtag": "#openseanfts",
    "post": 2
  },
  {
    "hashtag": "#nftcommmunity",
    "post": 2
  },
  {
    "hashtag": "#drawingart",
    "post": 2
  },
  {
    "hashtag": "#nftphotography",
    "post": 2
  },
  {
    "hashtag": "#matic",
    "post": 2
  },
  {
    "hashtag": "#btc",
    "post": 2
  },
  {
    "hashtag": "#tezos",
    "post": 2
  },
  {
    "hashtag": "#eth",
    "post": 2
  },
  {
    "hashtag": "#rariblenfts",
    "post": 1
  },
  {
    "hashtag": "#artwork",
    "post": 1
  },
  {
    "hashtag": "#artdigital",
    "post": 1
  },
  {
    "hashtag": "#artistontwitter",
    "post": 1
  },
  {
    "hashtag": "#drawing",
    "post": 1
  },
  {
    "hashtag": "#aiartwork",
    "post": 1
  },
  {
    "hashtag": "#aiartworks",
    "post": 1
  },
  {
    "hashtag": "#aiartists",
    "post": 1
  },
  {
    "hashtag": "#lordoftherings",
    "post": 1
  },
  {
    "hashtag": "#xartist",
    "post": 1
  },
  {
    "hashtag": "#ai",
    "post": 1
  },
  {
    "hashtag": "#trueweb3",
    "post": 1
  },
  {
    "hashtag": "#aiart",
    "post": 1
  },
  {
    "hashtag": "#ordi",
    "post": 1
  },
  {
    "hashtag": "#hive",
    "post": 1
  },
  {
    "hashtag": "#bilpcon",
    "post": 1
  },
  {
    "hashtag": "#bnb",
    "post": 1
  },
  {
    "hashtag": "#shib",
    "post": 1
  },
  {
    "hashtag": "#sundaymood",
    "post": 1
  },
  {
    "hashtag": "#art",
    "post": 1
  },
  {
    "hashtag": "#web3",
    "post": 1
  },
  {
    "hashtag": "#lunc",
    "post": 1
  },
  {
    "hashtag": "#etc",
    "post": 1
  },
  {
    "hashtag": "#bch",
    "post": 1
  },
  {
    "hashtag": "#newnft",
    "post": 1
  },
  {
    "hashtag": "#newupload",
    "post": 1
  },
  {
    "hashtag": "#ethereum",
    "post": 1
  },
  {
    "hashtag": "#solana",
    "post": 1
  },
  {
    "hashtag": "#polygon",
    "post": 1
  },
  {
    "hashtag": "#shillarts",
    "post": 1
  },
  {
    "hashtag": "#nftday",
    "post": 1
  },
  {
    "hashtag": "#nftdrops",
    "post": 1
  },
  {
    "hashtag": "#nftshill",
    "post": 1
  },
  {
    "hashtag": "#tezoscollector",
    "post": 1
  },
  {
    "hashtag": "#tezosarts",
    "post": 1
  },
  {
    "hashtag": "#objktcom",
    "post": 1
  },
  {
    "hashtag": "#music",
    "post": 1
  },
  {
    "hashtag": "#illustration",
    "post": 1
  },
  {
    "hashtag": "#frogatars",
    "post": 1
  },
  {
    "hashtag": "#cryptoart",
    "post": 1
  },
  {
    "hashtag": "#cryptoartist",
    "post": 1
  },
  {
    "hashtag": "#nftcollectors",
    "post": 1
  },
  {
    "hashtag": "#coinbase",
    "post": 1
  },
  {
    "hashtag": "#x2y2",
    "post": 1
  },
  {
    "hashtag": "#nftcollectibles",
    "post": 1
  },
  {
    "hashtag": "#raredigitalart",
    "post": 1
  },
  {
    "hashtag": "#nftcolectors",
    "post": 1
  },
  {
    "hashtag": "#nftcollection",
    "post": 1
  },
  {
    "hashtag": "#foundtion",
    "post": 1
  },
  {
    "hashtag": "#nftshilling",
    "post": 1
  },
  {
    "hashtag": "#nftcollections",
    "post": 1
  },
  {
    "hashtag": "#nftmint",
    "post": 1
  },
  {
    "hashtag": "#artgallery",
    "post": 1
  },
  {
    "hashtag": "#cryptoinvestor",
    "post": 1
  },
  {
    "hashtag": "#etherum",
    "post": 1
  },
  {
    "hashtag": "#oliverr",
    "post": 1
  }
]